grafana_color_constants/__init__.py
grafana_color_constants-0.1.2.dist-info/METADATA
grafana_color_constants-0.1.2.dist-info/WHEEL
grafana_color_constants-0.1.2.dist-info/top_level.txt
grafana_color_constants-0.1.2.dist-info/RECORD
