Metadata-Version: 2.1
Name: grafana-color-constants
Version: 0.1.2
Summary: Basic Class containing Grafana Color constants
Home-page: https://gitlab.com/calixtemayoraz/grafana-color-constants
Author: Calixte Mayoraz
Author-email: calixte.mayoraz@eversys.com
Classifier: Programming Language :: Python :: 3
Classifier: Operating System :: OS Independent
Requires-Python: >=3.7
Requires-Dist: m2r (==0.2.1)
